insupportable/.__init__.py.swp
insupportable/.__init__.py.un~
insupportable/.insupportable.py.un~
insupportable/__init__.py
insupportable/insupportable.py
insupportable-0.1.2.dist-info/METADATA
insupportable-0.1.2.dist-info/WHEEL
insupportable-0.1.2.dist-info/RECORD
