Metadata-Version: 1.2
Name: insupportable
Version: 0.1.2
Summary: a simple way to remember to remove dead code due to notanymore supported
Home-page: https://github.com/Carreau/insupportable
License: UNKNOWN
Author: Matthias Bussonnier
Author-email: bussonniermatthias@gmail.com
Classifier: License :: OSI Approved :: MIT License
